__init__.py
core/__init__.py
core/aggregated_normalized_measures.py
core/measures_functions.py
core/schemas.py
core/transformations.py
resources/__init__.py
resources/analysis.py
resources/constants.py
staticfiles/__init__.py
staticfiles/default_pre_config.py
staticfiles/supported_metrics.py
util/__init__.py
util/check.py
util/exceptions.py
util/run_time_data_operations.py
msgram_core-1.5.3.dist-info/LICENSE
msgram_core-1.5.3.dist-info/METADATA
msgram_core-1.5.3.dist-info/WHEEL
msgram_core-1.5.3.dist-info/top_level.txt
msgram_core-1.5.3.dist-info/RECORD
