Metadata-Version: 2.1
Name: msgram_core
Version: 1.5.3
Summary: The MeasureSoftGram-Core is a Software system for continuous quality of product observation and multidimensional use in continuous design engineering software and is where you have the innovative mathematical models for software analysis.
Author-email: MeasureSoftGram <measuresoftgram@gmail.com>
License: GNU AFFERO GENERAL PUBLIC LICENSE
Keywords: core,measures,quality,algebraic model
Classifier: Environment :: Console
Classifier: License :: OSI Approved :: GNU Affero General Public License v3 or later (AGPLv3+)
Classifier: Natural Language :: Portuguese (Brazilian)
Classifier: Operating System :: OS Independent
Classifier: Programming Language :: Python :: 3.8
Classifier: Topic :: Utilities
Requires-Python: >=3.9
License-File: LICENSE
Requires-Dist: pandas >=2.2.0
Requires-Dist: marshmallow ==3.21.0
Requires-Dist: numpy >=2.0
Requires-Dist: scikit-learn >=1.5.1
Requires-Dist: scipy >=1.14.1
